Metadata-Version: 1.1
Name: sort-example
Version: 0.1.0
Summary: A example Python package with sort methods
Home-page: UNKNOWN
Author: Artyom Kolosov
Author-email: UNKNOWN
License: UNKNOWN
Platform: UNKNOWN
Classifier: Programming Language :: Python :: 3
Classifier: Programming Language :: Python :: 3.4
Classifier: Programming Language :: Python :: 3.5
